blur_placeholder/__init__.py
blur_placeholder/async_core.py
blur_placeholder/cache.py
blur_placeholder/core.py
blur_placeholder/exceptions.py
blur_placeholder/utils.py
blur_placeholder-0.1.2.dist-info/licenses/LICENSE
blur_placeholder-0.1.2.dist-info/METADATA
blur_placeholder-0.1.2.dist-info/WHEEL
blur_placeholder-0.1.2.dist-info/top_level.txt
blur_placeholder-0.1.2.dist-info/RECORD
