Metadata-Version: 2.4
Name: blur_placeholder
Version: 0.1.2
Summary: Generate blurred image placeholders for lazy loading
License: ### `LICENSE`
Project-URL: Homepage, https://github.com/Njoro410/blur_placeholder
Project-URL: Documentation, https://github.com/Njoro410/blur_placeholder#readme
Project-URL: BugTracker, https://github.com/Njoro410/blur_placeholder/issues
Keywords: image,placeholder,blur,lazy-loading
Classifier: License :: OSI Approved :: MIT License
Classifier: Programming Language :: Python :: 3
Classifier: Programming Language :: Python :: 3.7
Classifier: Programming Language :: Python :: 3.8
Classifier: Programming Language :: Python :: 3.9
Classifier: Programming Language :: Python :: 3.10
Classifier: Programming Language :: Python :: 3.11
Classifier: Programming Language :: Python :: 3.12
Classifier: Operating System :: OS Independent
Classifier: Topic :: Multimedia :: Graphics
Classifier: Intended Audience :: Developers
Requires-Python: >=3.7
License-File: LICENSE
Requires-Dist: Pillow>=9.0.0
Requires-Dist: requests>=2.26.0
Provides-Extra: async
Requires-Dist: aiohttp>=3.8.0; extra == "async"
Provides-Extra: dev
Requires-Dist: pytest>=7.1.2; extra == "dev"
Requires-Dist: pytest-asyncio>=0.18.3; extra == "dev"
Requires-Dist: requests-mock>=1.9.3; extra == "dev"
Requires-Dist: twine>=4.0.0; extra == "dev"
Requires-Dist: build>=0.10.0; extra == "dev"
Dynamic: license-file
